Data Routing/mux8to1/mux.sv

module mux (
    input   logic   [2:0]   a,
    input   logic   [2:0]   b,
    input   logic   [2:0]   c,
    input   logic   [2:0]   d,
    input   logic   [2:0]   e,
    input   logic   [2:0]   f,
    input   logic   [2:0]   g,
    input   logic   [2:0]   h,
    input   logic   [2:0]   sel,
    output  logic   [2:0]   y
);
    
    always_comb begin : mux8to1
        case (sel)
            3'b000: y = a;
            3'b001: y = b;
            3'b010: y = c;
            3'b011: y = d;
            3'b100: y = e;
            3'b101: y = f;
            3'b110: y = g;
            3'b111: y = h; 
            default: y = 3'b000;
        endcase
    end

endmodule

Data Routing/mux8to1/mux_tb.sv
`timescale 1ps/1ps

module mux_tb;

    logic [2:0] a, b, c, d;
    logic [2:0] e, f, g, h, y;
    logic [2:0] sel;

    mux dut(
        .a(a),
        .b(b),
        .c(c),
        .d(d),
        .e(e),
        .f(f),
        .g(g),
        .h(h),
        .sel(sel),
        .y(y)
    );

    initial begin
        //Create waveform file
        $dumpfile("wave.vcd");
        $dumpvars(0, mux_tb);

        //Print values whenever they change
        $monitor("Time=%0t  a=%b  b=%b  c=%b  d=%b  e=%b  f=%b  g=%b  h=%b  sel=%b  y=%b", 
                $time, a, b, c, d, e, f, g, h, sel, y);

        //Apply test vectors
        a = 3'b000; b = 3'b001; c = 3'b010; d = 3'b011;
        e = 3'b100; f = 3'b101; g = 3'b110; h = 3'b111; sel=3'b000; #10;
        a = 3'b000; b = 3'b001; c = 3'b010; d = 3'b011;
        e = 3'b100; f = 3'b101; g = 3'b110; h = 3'b111; sel=3'b001; #10;
        a = 3'b000; b = 3'b001; c = 3'b010; d = 3'b011;
        e = 3'b100; f = 3'b101; g = 3'b110; h = 3'b111; sel=3'b010; #10;
        a = 3'b000; b = 3'b001; c = 3'b010; d = 3'b011;
        e = 3'b100; f = 3'b101; g = 3'b110; h = 3'b111; sel=3'b011; #10;
        a = 3'b000; b = 3'b001; c = 3'b010; d = 3'b011;
        e = 3'b100; f = 3'b101; g = 3'b110; h = 3'b111; sel=3'b100; #10;
        a = 3'b000; b = 3'b001; c = 3'b010; d = 3'b011;
        e = 3'b100; f = 3'b101; g = 3'b110; h = 3'b111; sel=3'b101; #10;
        a = 3'b000; b = 3'b001; c = 3'b010; d = 3'b011;
        e = 3'b100; f = 3'b101; g = 3'b110; h = 3'b111; sel=3'b110; #10;
        a = 3'b000; b = 3'b001; c = 3'b010; d = 3'b011;
        e = 3'b100; f = 3'b101; g = 3'b110; h = 3'b111; sel=3'b111; #10;

        $finish;
    end

endmodule

Data Routing/mux8to1/wave.vcd
$date
	Mon Aug  3 04:28:44 2026
$end
$version
	Icarus Verilog
$end
$timescale
	1ps
$end
$scope module mux_tb $end
$var wire 3 ! y [2:0] $end
$var reg 3 " a [2:0] $end
$var reg 3 # b [2:0] $end
$var reg 3 $ c [2:0] $end
$var reg 3 % d [2:0] $end
$var reg 3 & e [2:0] $end
$var reg 3 ' f [2:0] $end
$var reg 3 ( g [2:0] $end
$var reg 3 ) h [2:0] $end
$var reg 3 * sel [2:0] $end
$scope module dut $end
$var wire 3 + a [2:0] $end
$var wire 3 , b [2:0] $end
$var wire 3 - c [2:0] $end
$var wire 3 . d [2:0] $end
$var wire 3 / e [2:0] $end
$var wire 3 0 f [2:0] $end
$var wire 3 1 g [2:0] $end
$var wire 3 2 h [2:0] $end
$var wire 3 3 sel [2:0] $end
$var reg 3 4 y [2:0] $end
$scope begin mux8to1 $end
$upscope $end
$upscope $end
$upscope $end
$enddefinitions $end
$comment Show the parameter values. $end
$dumpall
$end
#0
$dumpvars
b0 4
b0 3
b111 2
b110 1
b101 0
b100 /
b11 .
b10 -
b1 ,
b0 +
b0 *
b111 )
b110 (
b101 '
b100 &
b11 %
b10 $
b1 #
b0 "
b0 !
$end
#10
b1 !
b1 4
b1 *
b1 3
#20
b10 !
b10 4
b10 *
b10 3
#30
b11 !
b11 4
b11 *
b11 3
#40
b100 !
b100 4
b100 *
b100 3
#50
b101 !
b101 4
b101 *
b101 3
#60
b110 !
b110 4
b110 *
b110 3
#70
b111 !
b111 4
b111 *
b111 3
